crabdeposit/__init__.py
crabdeposit/native_interface.py
crabdeposit-0.1.dist-info/licenses/LICENSE
crabdeposit-0.1.dist-info/METADATA
crabdeposit-0.1.dist-info/WHEEL
crabdeposit-0.1.dist-info/top_level.txt
crabdeposit-0.1.dist-info/RECORD
